LICENSE
README.md
setup.py
herolabsapi/__init__.py
herolabsapi/client.py
herolabsapi/const.py
herolabsapi/errors.py
herolabsapi/incidents.py
herolabsapi/properties.py
herolabsapi/signals.py
herolabsapi/sonic.py
herolabsapi/tests_async.py
herolabsapi/user.py
herolabsapi.egg-info/PKG-INFO
herolabsapi.egg-info/SOURCES.txt
herolabsapi.egg-info/dependency_links.txt
herolabsapi.egg-info/top_level.txt