Metadata-Version: 2.1
Name: herolabsapi
Version: 0.2.0
Summary: Python Library for Hero Labs API, creators of the Sonic smart water shut off valve
Home-page: https://github.com/markvader/herolabsapi
Author: Mark Breen
Author-email: markjbreen@gmail.com
License: MIT
Platform: UNKNOWN
License-File: LICENSE
